pymailtm/__init__.py
pymailtm/cli.py
pymailtm/pymailtm.py
pymailtm-1.1.1.dist-info/entry_points.txt
pymailtm-1.1.1.dist-info/LICENSE
pymailtm-1.1.1.dist-info/WHEEL
pymailtm-1.1.1.dist-info/METADATA
pymailtm-1.1.1.dist-info/RECORD
