Metadata-Version: 2.1
Name: pymailtm
Version: 1.1.1
Summary: A python web api wrapper and command line client for mail.tm.
Home-page: https://github.com/CarloDePieri/pymailtm
License: GPL-3.0-only
Keywords: mail,temp,mail.tm
Author: Carlo De Pieri
Author-email: depieri.carlo@gmail.com
Requires-Python: >=3.7,<4.0
Classifier: Development Status :: 5 - Production/Stable
Classifier: Environment :: Console
Classifier: Environment :: Web Environment
Classifier: Intended Audience :: Developers
Classifier: Intended Audience :: End Users/Desktop
Classifier: License :: OSI Approved :: GNU General Public License v3 (GPLv3)
Classifier: Programming Language :: Python :: 3
Classifier: Programming Language :: Python :: 3.10
Classifier: Programming Language :: Python :: 3.7
Classifier: Programming Language :: Python :: 3.8
Classifier: Programming Language :: Python :: 3.9
Classifier: Topic :: Communications :: Email
Classifier: Topic :: Communications :: Email :: Email Clients (MUA)
Classifier: Topic :: Utilities
Requires-Dist: pyperclip (>=1.8.2,<2.0.0)
Requires-Dist: random-username (>=1.0.2,<2.0.0)
Requires-Dist: requests (>=2.28.1,<3.0.0)
Project-URL: Repository, https://github.com/CarloDePieri/pymailtm
